.readthedocs.yml
.travis.yml
AUTHORS
ChangeLog
LICENSE
README.md
readthedocs.yml
requirements-dev.in
requirements-dev.txt
requirements.in
requirements.txt
setup.cfg
setup.py
tox.ini
docs/Makefile
docs/conf.py
docs/development.rst
docs/index.rst
docs/quickstart.rst
docs/reference.rst
hvac_cli/__init__.py
hvac_cli/cli.py
hvac_cli/cmd.py
hvac_cli/kv.py
hvac_cli/status.py
hvac_cli/version.py
hvac_cli.egg-info/PKG-INFO
hvac_cli.egg-info/SOURCES.txt
hvac_cli.egg-info/dependency_links.txt
hvac_cli.egg-info/entry_points.txt
hvac_cli.egg-info/not-zip-safe
hvac_cli.egg-info/pbr.json
hvac_cli.egg-info/requires.txt
hvac_cli.egg-info/top_level.txt
tests/__init__.py
tests/conftest.py
tests/modified_environ.py
tests/secrets.json
tests/test_cli.py
tests/test_cmd.py
tests/test_kv.py
tests/test_kv_cmd.py
tests/test_modified_environ.py
tests/test_status_cmd.py