Metadata-Version: 2.1
Name: hvac-cli
Version: 1.2.0
Summary: Hashicorp Vault CLI with additional features
Home-page: https://github.com/hvac/hvac-cli
Author: singuliere
Author-email: singuliere@autistici.org
License: Apache License 2.0
Project-URL: Bug Tracker, https://github.com/hvac/hvac-cli/issues
Project-URL: Documentation, https://hvac-cli.readthedocs.io/
Project-URL: Source Code, https://github.com/hvac/hvac-cli
Platform: UNKNOWN
Classifier: Development Status :: 4 - Beta
Classifier: Environment :: Console
Classifier: Intended Audience :: Developers
Classifier: Intended Audience :: Information Technology
Classifier: License :: OSI Approved :: Apache Software License
Classifier: Operating System :: OS Independent
Classifier: Programming Language :: Python :: 3
